backtesting/__init__.py
backtesting/_plotting.py
backtesting/_stats.py
backtesting/_util.py
backtesting/_version.py
backtesting/autoscale_cb.js
backtesting/backtesting.py
backtesting/lib.py
backtesting/smbo.py
backtesting/test/BTCUSD.csv
backtesting/test/EURUSD.csv
backtesting/test/GOOG.csv
backtesting/test/__init__.py
backtesting/test/__main__.py
backtesting/test/_test.py
backtesting-0.6.5.dist-info/LICENSE.md
backtesting-0.6.5.dist-info/METADATA
backtesting-0.6.5.dist-info/WHEEL
backtesting-0.6.5.dist-info/top_level.txt
backtesting-0.6.5.dist-info/RECORD
